{
  "project_info": {
    "project_number": "231991882358",
    "project_id": "farmer-s-app-49a6c",
    "storage_bucket": "farmer-s-app-49a6c.appspot.com"
  },
  "client": [
    {
      "client_info": {
        "mobilesdk_app_id": "1:231991882358:android:8e63610d8f62c1f9e4a557",
        "android_client_info": {
          "package_name": "com.farmerspp.com"
        }
      },
      "oauth_client": [
        {
          "client_id": "231991882358-cqna1vk85tpf0sfl5erf6t3vrkbo35hn.apps.googleusercontent.com",
          "client_type": 1,
          "android_info": {
            "package_name": "com.farmerspp.com",
            "certificate_hash": "6d0704b82cf2cc87dd5e397f8dc7ecde6c74c131"
          }
        },
        {
          "client_id": "231991882358-0uauoqko0841q34vc4b4tp8i2q1i7ide.apps.googleusercontent.com",
          "client_type": 3
        }
      ],
      "api_key": [
        {
          "current_key": "AIzaSyDOHKNaLWqAb6JVN8dCE1XGQwVsN-1RGZY"
        }
      ],
      "services": {
        "appinvite_service": {
          "other_platform_oauth_client": [
            {
              "client_id": "231991882358-0uauoqko0841q34vc4b4tp8i2q1i7ide.apps.googleusercontent.com",
              "client_type": 3
            }
          ]
        }
      }
    }
  ],
  "configuration_version": "1"
}